{
  "0": {
    "_dirName": "0",
    "_dirType": "sub",
    "1": {
      "_dirName": "1",
      "_dirType": "Int",
      "_value": 7
    },
    "5": {
      "_dirName": "5",
      "_dirType": "Int",
      "_value": 17
    },
    "8": {
      "_dirName": "8",
      "_dirType": "Int",
      "_value": 19
    }
  },
  "1": {
    "_dirName": "1",
    "_dirType": "sub",
    "10": {
      "_dirName": "10",
      "_dirType": "Int",
      "_value": 54
    },
    "12": {
      "_dirName": "12",
      "_dirType": "Int",
      "_value": 57
    },
    "15": {
      "_dirName": "15",
      "_dirType": "Int",
      "_value": 83
    },
    "20": {
      "_dirName": "20",
      "_dirType": "Int",
      "_value": 106
    },
    "22": {
      "_dirName": "22",
      "_dirType": "Int",
      "_value": 109
    },
    "25": {
      "_dirName": "25",
      "_dirType": "Int",
      "_value": 129
    },
    "30": {
      "_dirName": "30",
      "_dirType": "Int",
      "_value": 154
    },
    "35": {
      "_dirName": "35",
      "_dirType": "Int",
      "_value": 179
    },
    "40": {
      "_dirName": "40",
      "_dirType": "Int",
      "_value": 203
    },
    "47": {
      "_dirName": "47",
      "_dirType": "Int",
      "_value": 208
    },
    "50": {
      "_dirName": "50",
      "_dirType": "Int",
      "_value": 261
    },
    "55": {
      "_dirName": "55",
      "_dirType": "Int",
      "_value": 267
    },
    "60": {
      "_dirName": "60",
      "_dirType": "Int",
      "_value": 305
    },
    "65": {
      "_dirName": "65",
      "_dirType": "Int",
      "_value": 308
    },
    "70": {
      "_dirName": "70",
      "_dirType": "Int",
      "_value": 359
    },
    "75": {
      "_dirName": "75",
      "_dirType": "Int",
      "_value": 356
    },
    "80": {
      "_dirName": "80",
      "_dirType": "Int",
      "_value": 382
    },
    "85": {
      "_dirName": "85",
      "_dirType": "Int",
      "_value": 388
    },
    "90": {
      "_dirName": "90",
      "_dirType": "Int",
      "_value": 440
    },
    "95": {
      "_dirName": "95",
      "_dirType": "Int",
      "_value": 446
    },
    "100": {
      "_dirName": "100",
      "_dirType": "Int",
      "_value": 494
    }
  },
  "2": {
    "_dirName": "2",
    "_dirType": "sub",
    "8": {
      "_dirName": "8",
      "_dirType": "Int",
      "_value": 25
    },
    "10": {
      "_dirName": "10",
      "_dirType": "Int",
      "_value": 31
    },
    "13": {
      "_dirName": "13",
      "_dirType": "Int",
      "_value": 40
    },
    "15": {
      "_dirName": "15",
      "_dirType": "Int",
      "_value": 49
    },
    "18": {
      "_dirName": "18",
      "_dirType": "Int",
      "_value": 54
    },
    "20": {
      "_dirName": "20",
      "_dirType": "Int",
      "_value": 56
    },
    "25": {
      "_dirName": "25",
      "_dirType": "Int",
      "_value": 60
    },
    "28": {
      "_dirName": "28",
      "_dirType": "Int",
      "_value": 64
    },
    "30": {
      "_dirName": "30",
      "_dirType": "Int",
      "_value": 75
    },
    "33": {
      "_dirName": "33",
      "_dirType": "Int",
      "_value": 91
    },
    "35": {
      "_dirName": "35",
      "_dirType": "Int",
      "_value": 98
    },
    "40": {
      "_dirName": "40",
      "_dirType": "Int",
      "_value": 99
    },
    "48": {
      "_dirName": "48",
      "_dirType": "Int",
      "_value": 107
    },
    "50": {
      "_dirName": "50",
      "_dirType": "Int",
      "_value": 131
    },
    "55": {
      "_dirName": "55",
      "_dirType": "Int",
      "_value": 134
    },
    "58": {
      "_dirName": "58",
      "_dirType": "Int",
      "_value": 142
    },
    "60": {
      "_dirName": "60",
      "_dirType": "Int",
      "_value": 159
    },
    "65": {
      "_dirName": "65",
      "_dirType": "Int",
      "_value": 162
    },
    "68": {
      "_dirName": "68",
      "_dirType": "Int",
      "_value": 170
    },
    "70": {
      "_dirName": "70",
      "_dirType": "Int",
      "_value": 184
    },
    "75": {
      "_dirName": "75",
      "_dirType": "Int",
      "_value": 190
    },
    "78": {
      "_dirName": "78",
      "_dirType": "Int",
      "_value": 198
    },
    "80": {
      "_dirName": "80",
      "_dirType": "Int",
      "_value": 212
    },
    "85": {
      "_dirName": "85",
      "_dirType": "Int",
      "_value": 218
    },
    "88": {
      "_dirName": "88",
      "_dirType": "Int",
      "_value": 226
    },
    "90": {
      "_dirName": "90",
      "_dirType": "Int",
      "_value": 240
    },
    "95": {
      "_dirName": "95",
      "_dirType": "Int",
      "_value": 246
    },
    "98": {
      "_dirName": "98",
      "_dirType": "Int",
      "_value": 254
    },
    "100": {
      "_dirName": "100",
      "_dirType": "Int",
      "_value": 266
    }
  },
  "3": {
    "_dirName": "3",
    "_dirType": "sub",
    "10": {
      "_dirName": "10",
      "_dirType": "Int",
      "_value": 32
    },
    "15": {
      "_dirName": "15",
      "_dirType": "Int",
      "_value": 49
    },
    "20": {
      "_dirName": "20",
      "_dirType": "Int",
      "_value": 65
    },
    "25": {
      "_dirName": "25",
      "_dirType": "Int",
      "_value": 80
    },
    "30": {
      "_dirName": "30",
      "_dirType": "Int",
      "_value": 95
    },
    "35": {
      "_dirName": "35",
      "_dirType": "Int",
      "_value": 110
    },
    "40": {
      "_dirName": "40",
      "_dirType": "Int",
      "_value": 125
    },
    "50": {
      "_dirName": "50",
      "_dirType": "Int",
      "_value": 145
    },
    "55": {
      "_dirName": "55",
      "_dirType": "Int",
      "_value": 148
    },
    "60": {
      "_dirName": "60",
      "_dirType": "Int",
      "_value": 177
    },
    "65": {
      "_dirName": "65",
      "_dirType": "Int",
      "_value": 180
    },
    "70": {
      "_dirName": "70",
      "_dirType": "Int",
      "_value": 206
    },
    "75": {
      "_dirName": "75",
      "_dirType": "Int",
      "_value": 212
    },
    "80": {
      "_dirName": "80",
      "_dirType": "Int",
      "_value": 238
    },
    "85": {
      "_dirName": "85",
      "_dirType": "Int",
      "_value": 244
    },
    "90": {
      "_dirName": "90",
      "_dirType": "Int",
      "_value": 270
    },
    "95": {
      "_dirName": "95",
      "_dirType": "Int",
      "_value": 276
    },
    "100": {
      "_dirName": "100",
      "_dirType": "Int",
      "_value": 298
    }
  },
  "4": {
    "_dirName": "4",
    "_dirType": "sub",
    "10": {
      "_dirName": "10",
      "_dirType": "Int",
      "_value": 42
    },
    "15": {
      "_dirName": "15",
      "_dirType": "Int",
      "_value": 60
    },
    "20": {
      "_dirName": "20",
      "_dirType": "Int",
      "_value": 76
    },
    "22": {
      "_dirName": "22",
      "_dirType": "Int",
      "_value": 85
    },
    "25": {
      "_dirName": "25",
      "_dirType": "Int",
      "_value": 100
    },
    "30": {
      "_dirName": "30",
      "_dirType": "Int",
      "_value": 115
    },
    "32": {
      "_dirName": "32",
      "_dirType": "Int",
      "_value": 116
    },
    "35": {
      "_dirName": "35",
      "_dirType": "Int",
      "_value": 131
    },
    "37": {
      "_dirName": "37",
      "_dirType": "Int",
      "_value": 132
    },
    "40": {
      "_dirName": "40",
      "_dirType": "Int",
      "_value": 147
    },
    "50": {
      "_dirName": "50",
      "_dirType": "Int",
      "_value": 184
    },
    "55": {
      "_dirName": "55",
      "_dirType": "Int",
      "_value": 187
    },
    "60": {
      "_dirName": "60",
      "_dirType": "Int",
      "_value": 220
    },
    "65": {
      "_dirName": "65",
      "_dirType": "Int",
      "_value": 223
    },
    "70": {
      "_dirName": "70",
      "_dirType": "Int",
      "_value": 257
    },
    "75": {
      "_dirName": "75",
      "_dirType": "Int",
      "_value": 263
    },
    "80": {
      "_dirName": "80",
      "_dirType": "Int",
      "_value": 291
    },
    "85": {
      "_dirName": "85",
      "_dirType": "Int",
      "_value": 297
    },
    "90": {
      "_dirName": "90",
      "_dirType": "Int",
      "_value": 325
    },
    "95": {
      "_dirName": "95",
      "_dirType": "Int",
      "_value": 331
    },
    "100": {
      "_dirName": "100",
      "_dirType": "Int",
      "_value": 331
    }
  },
  "5": {
    "_dirName": "5",
    "_dirType": "sub",
    "10": {
      "_dirName": "10",
      "_dirType": "Int",
      "_value": 24
    },
    "15": {
      "_dirName": "15",
      "_dirType": "Int",
      "_value": 43
    },
    "20": {
      "_dirName": "20",
      "_dirType": "Int",
      "_value": 56
    },
    "25": {
      "_dirName": "25",
      "_dirType": "Int",
      "_value": 69
    },
    "30": {
      "_dirName": "30",
      "_dirType": "Int",
      "_value": 82
    },
    "35": {
      "_dirName": "35",
      "_dirType": "Int",
      "_value": 95
    },
    "40": {
      "_dirName": "40",
      "_dirType": "Int",
      "_value": 108
    },
    "50": {
      "_dirName": "50",
      "_dirType": "Int",
      "_value": 146
    },
    "55": {
      "_dirName": "55",
      "_dirType": "Int",
      "_value": 149
    },
    "60": {
      "_dirName": "60",
      "_dirType": "Int",
      "_value": 178
    },
    "65": {
      "_dirName": "65",
      "_dirType": "Int",
      "_value": 181
    },
    "70": {
      "_dirName": "70",
      "_dirType": "Int",
      "_value": 207
    },
    "75": {
      "_dirName": "75",
      "_dirType": "Int",
      "_value": 213
    },
    "80": {
      "_dirName": "80",
      "_dirType": "Int",
      "_value": 239
    },
    "85": {
      "_dirName": "85",
      "_dirType": "Int",
      "_value": 245
    },
    "90": {
      "_dirName": "90",
      "_dirType": "Int",
      "_value": 271
    },
    "100": {
      "_dirName": "100",
      "_dirType": "Int",
      "_value": 309
    }
  }
}