{
  "05743006": {
    "_dirName": "05743006",
    "_dirType": "sub",
    "info": {
      "_dirName": "info",
      "_dirType": "sub",
      "icon": {
        "_dirName": "icon",
        "_dirType": "canvas",
        "origin": {
          "_dirName": "origin",
          "_dirType": "vector",
          "_x": -3,
          "_y": 32
        },
        "_outlink": {
          "_dirName": "_outlink",
          "_dirType": "String",
          "_value": "Item/Cash/_Canvas/0574.img/05743006/info/icon"
        },
        "_width": 1,
        "_height": 1,
        "_format": 1,
        "_format2": 0
      },
      "iconRaw": {
        "_dirName": "iconRaw",
        "_dirType": "canvas",
        "origin": {
          "_dirName": "origin",
          "_dirType": "vector",
          "_x": -2,
          "_y": 32
        },
        "_outlink": {
          "_dirName": "_outlink",
          "_dirType": "String",
          "_value": "Item/Cash/_Canvas/0574.img/05743006/info/iconRaw"
        },
        "_width": 1,
        "_height": 1,
        "_format": 1,
        "_format2": 0
      },
      "cash": {
        "_dirName": "cash",
        "_dirType": "Int",
        "_value": 1
      }
    }
  },
  "05743004": {
    "_dirName": "05743004",
    "_dirType": "sub",
    "info": {
      "_dirName": "info",
      "_dirType": "sub",
      "icon": {
        "_dirName": "icon",
        "_dirType": "canvas",
        "origin": {
          "_dirName": "origin",
          "_dirType": "vector",
          "_x": -2,
          "_y": 32
        },
        "_outlink": {
          "_dirName": "_outlink",
          "_dirType": "String",
          "_value": "Item/Cash/_Canvas/0506.img/05060074/info/icon"
        },
        "_width": 1,
        "_height": 1,
        "_format": 1,
        "_format2": 0
      },
      "iconRaw": {
        "_dirName": "iconRaw",
        "_dirType": "canvas",
        "origin": {
          "_dirName": "origin",
          "_dirType": "vector",
          "_x": -3,
          "_y": 32
        },
        "_outlink": {
          "_dirName": "_outlink",
          "_dirType": "String",
          "_value": "Item/Cash/_Canvas/0506.img/05060074/info/iconRaw"
        },
        "_width": 1,
        "_height": 1,
        "_format": 1,
        "_format2": 0
      },
      "cash": {
        "_dirName": "cash",
        "_dirType": "Int",
        "_value": 1
      }
    }
  },
  "05743005": {
    "_dirName": "05743005",
    "_dirType": "sub",
    "info": {
      "_dirName": "info",
      "_dirType": "sub",
      "icon": {
        "_dirName": "icon",
        "_dirType": "canvas",
        "origin": {
          "_dirName": "origin",
          "_dirType": "vector",
          "_x": -2,
          "_y": 32
        },
        "_outlink": {
          "_dirName": "_outlink",
          "_dirType": "String",
          "_value": "Item/Cash/_Canvas/0506.img/05060075/info/icon"
        },
        "_width": 1,
        "_height": 1,
        "_format": 1,
        "_format2": 0
      },
      "iconRaw": {
        "_dirName": "iconRaw",
        "_dirType": "canvas",
        "origin": {
          "_dirName": "origin",
          "_dirType": "vector",
          "_x": -3,
          "_y": 32
        },
        "_outlink": {
          "_dirName": "_outlink",
          "_dirType": "String",
          "_value": "Item/Cash/_Canvas/0506.img/05060075/info/iconRaw"
        },
        "_width": 1,
        "_height": 1,
        "_format": 1,
        "_format2": 0
      },
      "cash": {
        "_dirName": "cash",
        "_dirType": "Int",
        "_value": 1
      }
    }
  },
  "05742001": {
    "_dirName": "05742001",
    "_dirType": "sub",
    "info": {
      "_dirName": "info",
      "_dirType": "sub",
      "icon": {
        "_dirName": "icon",
        "_dirType": "canvas",
        "origin": {
          "_dirName": "origin",
          "_dirType": "vector",
          "_x": -2,
          "_y": 32
        },
        "_outlink": {
          "_dirName": "_outlink",
          "_dirType": "String",
          "_value": "Item/Cash/_Canvas/0506.img/05060076/info/icon"
        },
        "_width": 1,
        "_height": 1,
        "_format": 1,
        "_format2": 0
      },
      "iconRaw": {
        "_dirName": "iconRaw",
        "_dirType": "canvas",
        "origin": {
          "_dirName": "origin",
          "_dirType": "vector",
          "_x": -3,
          "_y": 32
        },
        "_outlink": {
          "_dirName": "_outlink",
          "_dirType": "String",
          "_value": "Item/Cash/_Canvas/0506.img/05060076/info/iconRaw"
        },
        "_width": 1,
        "_height": 1,
        "_format": 1,
        "_format2": 0
      },
      "cash": {
        "_dirName": "cash",
        "_dirType": "Int",
        "_value": 1
      }
    }
  },
  "05742002": {
    "_dirName": "05742002",
    "_dirType": "sub",
    "info": {
      "_dirName": "info",
      "_dirType": "sub",
      "icon": {
        "_dirName": "icon",
        "_dirType": "canvas",
        "origin": {
          "_dirName": "origin",
          "_dirType": "vector",
          "_x": -2,
          "_y": 32
        },
        "_outlink": {
          "_dirName": "_outlink",
          "_dirType": "String",
          "_value": "Item/Cash/_Canvas/0506.img/05060079/info/icon"
        },
        "_width": 1,
        "_height": 1,
        "_format": 1,
        "_format2": 0
      },
      "iconRaw": {
        "_dirName": "iconRaw",
        "_dirType": "canvas",
        "origin": {
          "_dirName": "origin",
          "_dirType": "vector",
          "_x": -3,
          "_y": 32
        },
        "_outlink": {
          "_dirName": "_outlink",
          "_dirType": "String",
          "_value": "Item/Cash/_Canvas/0506.img/05060079/info/iconRaw"
        },
        "_width": 1,
        "_height": 1,
        "_format": 1,
        "_format2": 0
      },
      "cash": {
        "_dirName": "cash",
        "_dirType": "Int",
        "_value": 1
      }
    }
  },
  "05742003": {
    "_dirName": "05742003",
    "_dirType": "sub",
    "info": {
      "_dirName": "info",
      "_dirType": "sub",
      "icon": {
        "_dirName": "icon",
        "_dirType": "canvas",
        "origin": {
          "_dirName": "origin",
          "_dirType": "vector",
          "_x": -2,
          "_y": 32
        },
        "_outlink": {
          "_dirName": "_outlink",
          "_dirType": "String",
          "_value": "Item/Cash/_Canvas/0506.img/05060080/info/icon"
        },
        "_width": 1,
        "_height": 1,
        "_format": 1,
        "_format2": 0
      },
      "iconRaw": {
        "_dirName": "iconRaw",
        "_dirType": "canvas",
        "origin": {
          "_dirName": "origin",
          "_dirType": "vector",
          "_x": -3,
          "_y": 32
        },
        "_outlink": {
          "_dirName": "_outlink",
          "_dirType": "String",
          "_value": "Item/Cash/_Canvas/0506.img/05060080/info/iconRaw"
        },
        "_width": 1,
        "_height": 1,
        "_format": 1,
        "_format2": 0
      },
      "cash": {
        "_dirName": "cash",
        "_dirType": "Int",
        "_value": 1
      }
    }
  },
  "05742004": {
    "_dirName": "05742004",
    "_dirType": "sub",
    "info": {
      "_dirName": "info",
      "_dirType": "sub",
      "icon": {
        "_dirName": "icon",
        "_dirType": "canvas",
        "origin": {
          "_dirName": "origin",
          "_dirType": "vector",
          "_x": -1,
          "_y": 32
        },
        "_outlink": {
          "_dirName": "_outlink",
          "_dirType": "String",
          "_value": "Item/Cash/_Canvas/0506.img/05060081/info/icon"
        },
        "_width": 1,
        "_height": 1,
        "_format": 1,
        "_format2": 0
      },
      "iconRaw": {
        "_dirName": "iconRaw",
        "_dirType": "canvas",
        "origin": {
          "_dirName": "origin",
          "_dirType": "vector",
          "_x": -1,
          "_y": 32
        },
        "_outlink": {
          "_dirName": "_outlink",
          "_dirType": "String",
          "_value": "Item/Cash/_Canvas/0506.img/05060081/info/iconRaw"
        },
        "_width": 1,
        "_height": 1,
        "_format": 1,
        "_format2": 0
      },
      "cash": {
        "_dirName": "cash",
        "_dirType": "Int",
        "_value": 1
      }
    }
  }
}