{
  "info": {
    "_dirName": "info",
    "_dirType": "sub",
    "speak": {
      "_dirName": "speak",
      "_dirType": "sub",
      "0": {
        "_dirName": "0",
        "_dirType": "String",
        "_value": "n0"
      },
      "1": {
        "_dirName": "1",
        "_dirType": "String",
        "_value": "n1"
      },
      "2": {
        "_dirName": "2",
        "_dirType": "String",
        "_value": "n2"
      }
    }
  },
  "stand": {
    "_dirName": "stand",
    "_dirType": "sub",
    "0": {
      "_dirName": "0",
      "_dirType": "canvas",
      "origin": {
        "_dirName": "origin",
        "_dirType": "vector",
        "_x": 33,
        "_y": 67
      },
      "z": {
        "_dirName": "z",
        "_dirType": "Int",
        "_value": 0
      },
      "delay": {
        "_dirName": "delay",
        "_dirType": "Int",
        "_value": 500
      },
      "_width": 67,
      "_height": 67,
      "_format": 1,
      "_format2": 0
    },
    "1": {
      "_dirName": "1",
      "_dirType": "canvas",
      "origin": {
        "_dirName": "origin",
        "_dirType": "vector",
        "_x": 33,
        "_y": 67
      },
      "z": {
        "_dirName": "z",
        "_dirType": "Int",
        "_value": 0
      },
      "delay": {
        "_dirName": "delay",
        "_dirType": "Int",
        "_value": 250
      },
      "_width": 67,
      "_height": 67,
      "_format": 1,
      "_format2": 0
    },
    "2": {
      "_dirName": "2",
      "_dirType": "canvas",
      "origin": {
        "_dirName": "origin",
        "_dirType": "vector",
        "_x": 33,
        "_y": 67
      },
      "z": {
        "_dirName": "z",
        "_dirType": "Int",
        "_value": 0
      },
      "delay": {
        "_dirName": "delay",
        "_dirType": "Int",
        "_value": 120
      },
      "_width": 67,
      "_height": 67,
      "_format": 1,
      "_format2": 0
    },
    "3": {
      "_dirName": "3",
      "_dirType": "canvas",
      "origin": {
        "_dirName": "origin",
        "_dirType": "vector",
        "_x": 33,
        "_y": 67
      },
      "z": {
        "_dirName": "z",
        "_dirType": "Int",
        "_value": 0
      },
      "delay": {
        "_dirName": "delay",
        "_dirType": "Int",
        "_value": 120
      },
      "_width": 67,
      "_height": 67,
      "_format": 1,
      "_format2": 0
    },
    "4": {
      "_dirName": "4",
      "_dirType": "canvas",
      "origin": {
        "_dirName": "origin",
        "_dirType": "vector",
        "_x": 33,
        "_y": 67
      },
      "z": {
        "_dirName": "z",
        "_dirType": "Int",
        "_value": 0
      },
      "delay": {
        "_dirName": "delay",
        "_dirType": "Int",
        "_value": 120
      },
      "_width": 67,
      "_height": 67,
      "_format": 1,
      "_format2": 0
    },
    "5": {
      "_dirName": "5",
      "_dirType": "uol",
      "_value": "0"
    }
  },
  "shake": {
    "_dirName": "shake",
    "_dirType": "sub",
    "0": {
      "_dirName": "0",
      "_dirType": "canvas",
      "origin": {
        "_dirName": "origin",
        "_dirType": "vector",
        "_x": 33,
        "_y": 67
      },
      "z": {
        "_dirName": "z",
        "_dirType": "Int",
        "_value": 0
      },
      "delay": {
        "_dirName": "delay",
        "_dirType": "Int",
        "_value": 300
      },
      "_width": 67,
      "_height": 67,
      "_format": 1,
      "_format2": 0
    },
    "1": {
      "_dirName": "1",
      "_dirType": "canvas",
      "origin": {
        "_dirName": "origin",
        "_dirType": "vector",
        "_x": 33,
        "_y": 67
      },
      "z": {
        "_dirName": "z",
        "_dirType": "Int",
        "_value": 0
      },
      "delay": {
        "_dirName": "delay",
        "_dirType": "Int",
        "_value": 150
      },
      "_width": 67,
      "_height": 67,
      "_format": 1,
      "_format2": 0
    },
    "2": {
      "_dirName": "2",
      "_dirType": "canvas",
      "origin": {
        "_dirName": "origin",
        "_dirType": "vector",
        "_x": 33,
        "_y": 67
      },
      "z": {
        "_dirName": "z",
        "_dirType": "Int",
        "_value": 0
      },
      "delay": {
        "_dirName": "delay",
        "_dirType": "Int",
        "_value": 300
      },
      "_width": 67,
      "_height": 67,
      "_format": 1,
      "_format2": 0
    },
    "3": {
      "_dirName": "3",
      "_dirType": "uol",
      "_value": "1"
    },
    "4": {
      "_dirName": "4",
      "_dirType": "uol",
      "_value": "0"
    },
    "5": {
      "_dirName": "5",
      "_dirType": "uol",
      "_value": "1"
    },
    "6": {
      "_dirName": "6",
      "_dirType": "uol",
      "_value": "2"
    },
    "7": {
      "_dirName": "7",
      "_dirType": "uol",
      "_value": "1"
    },
    "8": {
      "_dirName": "8",
      "_dirType": "uol",
      "_value": "0"
    }
  },
  "what": {
    "_dirName": "what",
    "_dirType": "sub",
    "0": {
      "_dirName": "0",
      "_dirType": "canvas",
      "origin": {
        "_dirName": "origin",
        "_dirType": "vector",
        "_x": 33,
        "_y": 67
      },
      "z": {
        "_dirName": "z",
        "_dirType": "Int",
        "_value": 0
      },
      "delay": {
        "_dirName": "delay",
        "_dirType": "Int",
        "_value": 500
      },
      "_width": 67,
      "_height": 67,
      "_format": 1,
      "_format2": 0
    },
    "1": {
      "_dirName": "1",
      "_dirType": "canvas",
      "origin": {
        "_dirName": "origin",
        "_dirType": "vector",
        "_x": 33,
        "_y": 67
      },
      "z": {
        "_dirName": "z",
        "_dirType": "Int",
        "_value": 0
      },
      "delay": {
        "_dirName": "delay",
        "_dirType": "Int",
        "_value": 100
      },
      "_width": 67,
      "_height": 67,
      "_format": 1,
      "_format2": 0
    },
    "2": {
      "_dirName": "2",
      "_dirType": "canvas",
      "origin": {
        "_dirName": "origin",
        "_dirType": "vector",
        "_x": 33,
        "_y": 67
      },
      "z": {
        "_dirName": "z",
        "_dirType": "Int",
        "_value": 0
      },
      "delay": {
        "_dirName": "delay",
        "_dirType": "Int",
        "_value": 100
      },
      "_width": 67,
      "_height": 67,
      "_format": 1,
      "_format2": 0
    },
    "3": {
      "_dirName": "3",
      "_dirType": "canvas",
      "origin": {
        "_dirName": "origin",
        "_dirType": "vector",
        "_x": 33,
        "_y": 67
      },
      "z": {
        "_dirName": "z",
        "_dirType": "Int",
        "_value": 0
      },
      "delay": {
        "_dirName": "delay",
        "_dirType": "Int",
        "_value": 500
      },
      "_width": 67,
      "_height": 67,
      "_format": 1,
      "_format2": 0
    },
    "4": {
      "_dirName": "4",
      "_dirType": "canvas",
      "origin": {
        "_dirName": "origin",
        "_dirType": "vector",
        "_x": 33,
        "_y": 67
      },
      "z": {
        "_dirName": "z",
        "_dirType": "Int",
        "_value": 0
      },
      "delay": {
        "_dirName": "delay",
        "_dirType": "Int",
        "_value": 500
      },
      "_width": 74,
      "_height": 67,
      "_format": 1,
      "_format2": 0
    },
    "5": {
      "_dirName": "5",
      "_dirType": "canvas",
      "origin": {
        "_dirName": "origin",
        "_dirType": "vector",
        "_x": 33,
        "_y": 67
      },
      "z": {
        "_dirName": "z",
        "_dirType": "Int",
        "_value": 0
      },
      "delay": {
        "_dirName": "delay",
        "_dirType": "Int",
        "_value": 100
      },
      "_width": 74,
      "_height": 67,
      "_format": 1,
      "_format2": 0
    },
    "6": {
      "_dirName": "6",
      "_dirType": "uol",
      "_value": "4"
    },
    "7": {
      "_dirName": "7",
      "_dirType": "canvas",
      "origin": {
        "_dirName": "origin",
        "_dirType": "vector",
        "_x": 33,
        "_y": 67
      },
      "z": {
        "_dirName": "z",
        "_dirType": "Int",
        "_value": 0
      },
      "delay": {
        "_dirName": "delay",
        "_dirType": "Int",
        "_value": 500
      },
      "_width": 67,
      "_height": 67,
      "_format": 1,
      "_format2": 0
    }
  },
  "fish": {
    "_dirName": "fish",
    "_dirType": "sub",
    "0": {
      "_dirName": "0",
      "_dirType": "canvas",
      "origin": {
        "_dirName": "origin",
        "_dirType": "vector",
        "_x": 33,
        "_y": 67
      },
      "z": {
        "_dirName": "z",
        "_dirType": "Int",
        "_value": 0
      },
      "delay": {
        "_dirName": "delay",
        "_dirType": "Int",
        "_value": 100
      },
      "_width": 67,
      "_height": 67,
      "_format": 1,
      "_format2": 0
    },
    "1": {
      "_dirName": "1",
      "_dirType": "canvas",
      "origin": {
        "_dirName": "origin",
        "_dirType": "vector",
        "_x": 33,
        "_y": 67
      },
      "z": {
        "_dirName": "z",
        "_dirType": "Int",
        "_value": 0
      },
      "delay": {
        "_dirName": "delay",
        "_dirType": "Int",
        "_value": 100
      },
      "_width": 67,
      "_height": 67,
      "_format": 1,
      "_format2": 0
    },
    "2": {
      "_dirName": "2",
      "_dirType": "canvas",
      "origin": {
        "_dirName": "origin",
        "_dirType": "vector",
        "_x": 33,
        "_y": 67
      },
      "z": {
        "_dirName": "z",
        "_dirType": "Int",
        "_value": 0
      },
      "delay": {
        "_dirName": "delay",
        "_dirType": "Int",
        "_value": 100
      },
      "_width": 67,
      "_height": 67,
      "_format": 1,
      "_format2": 0
    },
    "3": {
      "_dirName": "3",
      "_dirType": "canvas",
      "origin": {
        "_dirName": "origin",
        "_dirType": "vector",
        "_x": 33,
        "_y": 67
      },
      "z": {
        "_dirName": "z",
        "_dirType": "Int",
        "_value": 0
      },
      "delay": {
        "_dirName": "delay",
        "_dirType": "Int",
        "_value": 1500
      },
      "_width": 67,
      "_height": 67,
      "_format": 1,
      "_format2": 0
    },
    "4": {
      "_dirName": "4",
      "_dirType": "uol",
      "_value": "2"
    },
    "5": {
      "_dirName": "5",
      "_dirType": "uol",
      "_value": "1"
    },
    "6": {
      "_dirName": "6",
      "_dirType": "uol",
      "_value": "0"
    },
    "7": {
      "_dirName": "7",
      "_dirType": "canvas",
      "origin": {
        "_dirName": "origin",
        "_dirType": "vector",
        "_x": 33,
        "_y": 67
      },
      "z": {
        "_dirName": "z",
        "_dirType": "Int",
        "_value": 0
      },
      "delay": {
        "_dirName": "delay",
        "_dirType": "Int",
        "_value": 1500
      },
      "_width": 67,
      "_height": 67,
      "_format": 1,
      "_format2": 0
    }
  }
}